MANIFEST.in
py26-requirements.txt
requirements.txt
setup.py
test-requirements.txt
asynx/__init__.py
asynx/taskqueue.py
asynx/version.txt
asynx.egg-info/PKG-INFO
asynx.egg-info/SOURCES.txt
asynx.egg-info/dependency_links.txt
asynx.egg-info/requires.txt
asynx.egg-info/top_level.txt
asynx.egg-info/zip-safe
tests/__init__.py
tests/test_tqclient.py